AntiMALReverse/__init__.py
AntiMALReverse/code_flow_analysis.py
AntiMALReverse/disassembly.py
AntiMALReverse/model.py
AntiMALReverse/obfuscation_removal.py
AntiMALReverse/reverse_engineering.py
AntiMALReverse/string_resource_extraction.py
AntiMALReverse/models/obfuscation_model.pth
AntiMALReverse-0.2.dist-info/METADATA
AntiMALReverse-0.2.dist-info/WHEEL
AntiMALReverse-0.2.dist-info/top_level.txt
AntiMALReverse-0.2.dist-info/RECORD
