Metadata-Version: 2.1
Name: AntiMALReverse
Version: 0.2
Summary: A novel reverse engineering toolkit for detecting and analyzing malware.
Home-page: https://github.com/codewithjoymondal
Author: Joy Mondal
Author-email: contact.joymondal@gmail.com
Classifier: Programming Language :: Python :: 3
Classifier: License :: OSI Approved :: MIT License
Classifier: Operating System :: OS Independent
Requires-Python: >=3.6
Requires-Dist: networkx
Requires-Dist: numpy
Requires-Dist: pandas
Requires-Dist: pefile
Requires-Dist: scikit-learn
Requires-Dist: torch
